asyncpgw/__init__.py
asyncpgw/general.py
asyncpgw/start.py
asyncpgw-0.3.6.dist-info/LICENSE
asyncpgw-0.3.6.dist-info/METADATA
asyncpgw-0.3.6.dist-info/WHEEL
asyncpgw-0.3.6.dist-info/top_level.txt
asyncpgw-0.3.6.dist-info/RECORD
