Metadata-Version: 2.1
Name: asyncpgw
Version: 0.3.6
Summary: これはdiscordpyとasyncpgを使用し、POSTTGRESQLにデータを保存する処理があるBOTを作ってる日本人向けに作成したものです
Home-page: https://github.com/furimu1234/asyncpgw/tree/main/asyncpgw
Author: furimu
License: UNKNOWN
Platform: UNKNOWN
Classifier: Programming Language :: Python :: 3.8
Classifier: License :: OSI Approved :: MIT License
Classifier: Operating System :: OS Independent
Requires-Dist: asyncpg
